Metadata-Version: 2.1
Name: nfc2mqtt
Version: 0.1.6
Summary: nfc2mqtt reads NFC tags with nfcpy and push them to MQTT
Home-page: UNKNOWN
Author: Bartosz Kupidura
Author-email: bartosz.kupidura@gmail.com
License: UNKNOWN
Platform: UNKNOWN
